{
  "content": "(a) In which configuration the system is not in equilibrium?\n(b) In which configuration is the system in (i) stable, and (ii) unstable equilibrium?\n(c) Which configuration corresponds to the lowest potential energy among all the configurations shown?\n\n![img-6.jpeg](images/image_5_6.jpeg)\nFIGURE 5.4",
  "header_path": "5.2.4 The electrostatic analog",
  "line_ranges": [
    [
      154,
      156
    ],
    [
      158,
      159
    ]
  ],
  "source_file": "output/leph105/leph105.md",
  "chunk_index": 37,
  "total_chunks_in_file": 129,
  "summary": "This text introduces a hypothetical question about the magnetic assosciated with a particle accelerator and answers the question in relation to the electrostatic analogy for particle accelerator.",
  "hypothetical_questions": [
    "Building an intuituve picture about the magnetic field vectors associated with a particle accelerator."
  ],
  "keywords": [
    "Particle Accelerator",
    "Magnetic Field",
    "Trajectory",
    "Orbital",
    "Electrostatic Analogy"
  ],
  "global_chunk_index": 37
}